package/__init__.py
package/clip.py
package/create.py
package/display.py
package/show.py
package/test.py
package/write.py
package/scrap/__init__.py
package/scrap/grab.py
package/stash/__init__.py
package/stash/test.py
fghsrt-1.0.dist-info/LICENSE
fghsrt-1.0.dist-info/METADATA
fghsrt-1.0.dist-info/WHEEL
fghsrt-1.0.dist-info/top_level.txt
fghsrt-1.0.dist-info/RECORD
