Metadata-Version: 2.1
Name: fghsrt
Version: 1.0
Summary: This is a package that does something Sneaky
Author: yashksaini-coder
Author-email: ys3853428@gmail.com
License: GPL 3.0
License-File: LICENSE
